Metadata-Version: 2.1
Name: calibrestekje
Version: 0.0.3
Summary: Library prototyping based on Calibre.
Home-page: https://github.com/decentral1se/calibrestekje
Author: decentral1se
Author-email: lukewm@riseup.net
Maintainer: decentral1se
Maintainer-email: lukewm@riseup.net
License: GPLv3
Project-URL: Source Code, https://github.com/decentral1se/calibrestekje
Project-URL: Documentation, https://calibrestekje.readthedocs.io/
Project-URL: Maintainer Support, https://liberapay.com/decentral1se/
Platform: UNKNOWN
Classifier: Programming Language :: Python :: 3
Classifier: Programming Language :: Python :: 3.6
Classifier: Programming Language :: Python :: 3.7
Classifier: Programming Language :: Python :: 3.8
Requires-Python: >=3.6
Provides-Extra: docs
Provides-Extra: changelog
